CHANGELOG.md
MANIFEST.in
README.md
setup.cfg
setup.py
versioneer.py
src/libreflow/__init__.py
src/libreflow.extensions.anpo.ui.egg-info/PKG-INFO
src/libreflow.extensions.anpo.ui.egg-info/SOURCES.txt
src/libreflow.extensions.anpo.ui.egg-info/dependency_links.txt
src/libreflow.extensions.anpo.ui.egg-info/top_level.txt
src/libreflow/extensions/__init__.py
src/libreflow/extensions/anpo/__init__.py
src/libreflow/extensions/anpo/ui/__init__.py
src/libreflow/extensions/anpo/ui/_version.py